aksharamukha/Convert.py
aksharamukha/ConvertDocx.py
aksharamukha/ConvertFix.py
aksharamukha/GeneralMap.py
aksharamukha/PostOptions.py
aksharamukha/PostProcess.py
aksharamukha/PreOptions.py
aksharamukha/PreProcess.py
aksharamukha/__init__.py
aksharamukha/gimeltra.py
aksharamukha/transliterate.py
aksharamukha/ScriptMap/FallBack.py
aksharamukha/ScriptMap/__init__.py
aksharamukha/ScriptMap/EastIndic/Balinese.py
aksharamukha/ScriptMap/EastIndic/BatakKaro.py
aksharamukha/ScriptMap/EastIndic/BatakManda.py
aksharamukha/ScriptMap/EastIndic/BatakPakpak.py
aksharamukha/ScriptMap/EastIndic/BatakSima.py
aksharamukha/ScriptMap/EastIndic/BatakToba.py
aksharamukha/ScriptMap/EastIndic/Buginese.py
aksharamukha/ScriptMap/EastIndic/Buhid.py
aksharamukha/ScriptMap/EastIndic/Burmese.py
aksharamukha/ScriptMap/EastIndic/Cham.py
aksharamukha/ScriptMap/EastIndic/Hanunoo.py
aksharamukha/ScriptMap/EastIndic/Javanese.py
aksharamukha/ScriptMap/EastIndic/Kawi.py
aksharamukha/ScriptMap/EastIndic/KhamtiShan.py
aksharamukha/ScriptMap/EastIndic/Khmer.py
aksharamukha/ScriptMap/EastIndic/KhomThai.py
aksharamukha/ScriptMap/EastIndic/KhuenTham.py
aksharamukha/ScriptMap/EastIndic/Lao.py
aksharamukha/ScriptMap/EastIndic/Lao2.py
aksharamukha/ScriptMap/EastIndic/LaoPali.py
aksharamukha/ScriptMap/EastIndic/LaoTham.py
aksharamukha/ScriptMap/EastIndic/LueTham.py
aksharamukha/ScriptMap/EastIndic/Makasar.py
aksharamukha/ScriptMap/EastIndic/Marchen.py
aksharamukha/ScriptMap/EastIndic/Mon.py
aksharamukha/ScriptMap/EastIndic/Pallava.py
aksharamukha/ScriptMap/EastIndic/PhagsPa.py
aksharamukha/ScriptMap/EastIndic/Rejang.py
aksharamukha/ScriptMap/EastIndic/Shan.py
aksharamukha/ScriptMap/EastIndic/Siddham.py
aksharamukha/ScriptMap/EastIndic/SiddhamRanjana.py
aksharamukha/ScriptMap/EastIndic/Soyombo.py
aksharamukha/ScriptMap/EastIndic/Sundanese.py
aksharamukha/ScriptMap/EastIndic/Tagalog.py
aksharamukha/ScriptMap/EastIndic/Tagbanwa.py
aksharamukha/ScriptMap/EastIndic/TaiLaing.py
aksharamukha_docx-2.2.0.dist-info/METADATA
aksharamukha_docx-2.2.0.dist-info/WHEEL
aksharamukha_docx-2.2.0.dist-info/top_level.txt
aksharamukha_docx-2.2.0.dist-info/RECORD
