Metadata-Version: 2.1
Name: aksharamukha-docx
Version: 2.2.0
Summary: Provides script conversion (a.k.a transliteration) between various scripts
Home-page: https://github.com/virtualvinodh/aksharamukha-python
Author: Vinodh Rajan
Author-email: vinodh@virtualvindh.com
License: GNU AGPL 3.0
Keywords: unicode semitic arabic syriac hebrew indic indian language script brahmi brahmic asian transliteration conversion writing alphabet romanization
Classifier: Development Status :: 5 - Production/Stable
Classifier: Intended Audience :: Education
Classifier: Intended Audience :: Science/Research
Classifier: Intended Audience :: Developers
Classifier: Natural Language :: Tamil
Classifier: Natural Language :: Telugu
Classifier: Natural Language :: Hindi
Classifier: Natural Language :: Marathi
Classifier: Natural Language :: Bengali
Classifier: Natural Language :: Urdu
Classifier: Natural Language :: Thai
Classifier: Natural Language :: Tibetan
Classifier: Natural Language :: Hebrew
Classifier: Natural Language :: Arabic
Classifier: Topic :: Text Processing :: Linguistic
Classifier: License :: OSI Approved :: GNU Affero General Public License v3
Classifier: Programming Language :: Python :: 3.8
Classifier: Programming Language :: Python :: 3.9
Classifier: Programming Language :: Python :: 3.10
Requires-Dist: Requests (>=2.20.1)
Requires-Dist: pykakasi (>=2.0.6)
Requires-Dist: pyyaml (>=5.4.1)
Requires-Dist: langcodes (>=3.1.0)
Requires-Dist: language-data
Requires-Dist: regex (>=2021.8.3)
Requires-Dist: fonttools[unicode] (>=4.27)
Requires-Dist: lxml
